README.md
setup.py
distributions/Binomialdistribution.py
distributions/Gaussiandistribution.py
distributions/Generaldistribution.py
distributions/__init__.py
pydist_prob.egg-info/PKG-INFO
pydist_prob.egg-info/SOURCES.txt
pydist_prob.egg-info/dependency_links.txt
pydist_prob.egg-info/not-zip-safe
pydist_prob.egg-info/top_level.txt