Metadata-Version: 1.0
Name: pydist-prob
Version: 0.3
Summary: Gaussian and binomial distributions
Home-page: UNKNOWN
Author: Elahi Concha
Author-email: elijahshellsanchez@outlook.com
License: MIT
Platform: UNKNOWN
